CHANGELOG.md
LICENSE
README.md
uvicorn_configurable/__init__.py
uvicorn_configurable/_version.py
uvicorn_configurable/config.py
uvicorn_configurable/py.typed
uvicorn_configurable-0.1.0.dist-info/LICENSE
uvicorn_configurable-0.1.0.dist-info/METADATA
uvicorn_configurable-0.1.0.dist-info/WHEEL
uvicorn_configurable-0.1.0.dist-info/RECORD
