Metadata-Version: 2.1
Name: uvicorn_configurable
Version: 0.1.0
Summary: Adds an application_settings ConfigSection to uvicorn
Home-page: https://github.com/StockwatchDev/uvicorn_configurable
License: MIT
Keywords: uvicorn,asgi web server,configuration,application_settings,dataclass,pydantic,toml
Author: Stockwatchdevs
Author-email: stockwatchdevs@gmail.com
Requires-Python: >=3.10,<4.0
Classifier: Development Status :: 4 - Beta
Classifier: Intended Audience :: Developers
Classifier: License :: OSI Approved :: MIT License
Classifier: Natural Language :: English
Classifier: Operating System :: OS Independent
Classifier: Programming Language :: Python :: 3
Classifier: Programming Language :: Python :: 3.10
Classifier: Programming Language :: Python :: 3.11
Classifier: Programming Language :: Python :: 3.12
Classifier: Programming Language :: Python :: 3.13
Classifier: Topic :: Software Development :: Libraries :: Python Modules
Classifier: Typing :: Typed
Requires-Dist: application-settings (>=0.5)
Project-URL: Repository, https://github.com/StockwatchDev/uvicorn_configurable
